sqlalchemy-stubs/__init__.pyi
sqlalchemy-stubs/_typing.pyi
sqlalchemy-stubs/events.pyi
sqlalchemy-stubs/exc.pyi
sqlalchemy-stubs/inspection.pyi
sqlalchemy-stubs/log.pyi
sqlalchemy-stubs/processors.pyi
sqlalchemy-stubs/schema.pyi
sqlalchemy-stubs/types.pyi
sqlalchemy-stubs/connectors/__init__.pyi
sqlalchemy-stubs/connectors/mxodbc.pyi
sqlalchemy-stubs/connectors/pyodbc.pyi
sqlalchemy-stubs/databases/__init__.pyi
sqlalchemy-stubs/dialects/__init__.pyi
sqlalchemy-stubs/dialects/firebird/__init__.pyi
sqlalchemy-stubs/dialects/firebird/base.pyi
sqlalchemy-stubs/dialects/firebird/fdb.pyi
sqlalchemy-stubs/dialects/firebird/kinterbasdb.pyi
sqlalchemy-stubs/dialects/mssql/__init__.pyi
sqlalchemy-stubs/dialects/mssql/base.pyi
sqlalchemy-stubs/dialects/mssql/information_schema.pyi
sqlalchemy-stubs/dialects/mssql/json.pyi
sqlalchemy-stubs/dialects/mssql/mxodbc.pyi
sqlalchemy-stubs/dialects/mssql/provision.pyi
sqlalchemy-stubs/dialects/mssql/pymssql.pyi
sqlalchemy-stubs/dialects/mssql/pyodbc.pyi
sqlalchemy-stubs/dialects/mysql/__init__.pyi
sqlalchemy-stubs/dialects/mysql/aiomysql.pyi
sqlalchemy-stubs/dialects/mysql/base.pyi
sqlalchemy-stubs/dialects/mysql/cymysql.pyi
sqlalchemy-stubs/dialects/mysql/dml.pyi
sqlalchemy-stubs/dialects/mysql/enumerated.pyi
sqlalchemy-stubs/dialects/mysql/json.pyi
sqlalchemy-stubs/dialects/mysql/mariadb.pyi
sqlalchemy-stubs/dialects/mysql/mariadbconnector.pyi
sqlalchemy-stubs/dialects/mysql/mysqlconnector.pyi
sqlalchemy-stubs/dialects/mysql/mysqldb.pyi
sqlalchemy-stubs/dialects/mysql/oursql.pyi
sqlalchemy-stubs/dialects/mysql/provision.pyi
sqlalchemy-stubs/dialects/mysql/pymysql.pyi
sqlalchemy-stubs/dialects/mysql/pyodbc.pyi
sqlalchemy-stubs/dialects/mysql/reflection.pyi
sqlalchemy-stubs/dialects/mysql/types.pyi
sqlalchemy-stubs/dialects/oracle/__init__.pyi
sqlalchemy-stubs/dialects/oracle/base.pyi
sqlalchemy-stubs/dialects/oracle/cx_oracle.pyi
sqlalchemy-stubs/dialects/oracle/provision.pyi
sqlalchemy-stubs/dialects/postgresql/__init__.pyi
sqlalchemy2_stubs-0.0.2a38.dist-info/LICENSE
sqlalchemy2_stubs-0.0.2a38.dist-info/METADATA
sqlalchemy2_stubs-0.0.2a38.dist-info/WHEEL
sqlalchemy2_stubs-0.0.2a38.dist-info/top_level.txt
sqlalchemy2_stubs-0.0.2a38.dist-info/RECORD
