Metadata-Version: 2.1
Name: sqlalchemy2-stubs
Version: 0.0.2a38
Summary: Typing Stubs for SQLAlchemy 1.4
Home-page: http://www.sqlalchemy.org
Author: Mike Bayer
Author-email: mike_mp@zzzcomputing.com
License: MIT
Project-URL: Issue Tracker, https://github.com/sqlalchemy/sqlalchemy2-stubs/
Classifier: Development Status :: 3 - Alpha
Classifier: Intended Audience :: Developers
Classifier: License :: OSI Approved :: MIT License
Classifier: Operating System :: OS Independent
Classifier: Programming Language :: Python :: 3
Classifier: Programming Language :: Python :: 3.6
Classifier: Programming Language :: Python :: 3.7
Classifier: Programming Language :: Python :: 3.8
Classifier: Programming Language :: Python :: 3.9
Classifier: Programming Language :: Python :: Implementation :: CPython
Classifier: Programming Language :: Python :: Implementation :: PyPy
Requires-Python: >=3.6
License-File: LICENSE
Requires-Dist: typing-extensions>=3.7.4
